feedback_bot/__init__.py
feedback_bot/feedback_bot.py
feedback_bot/helpers.py
tg_feedback_bot_ru-0.2.13.dist-info/LICENSE
tg_feedback_bot_ru-0.2.13.dist-info/METADATA
tg_feedback_bot_ru-0.2.13.dist-info/WHEEL
tg_feedback_bot_ru-0.2.13.dist-info/entry_points.txt
tg_feedback_bot_ru-0.2.13.dist-info/top_level.txt
tg_feedback_bot_ru-0.2.13.dist-info/RECORD
