Metadata-Version: 2.1
Name: tg-feedback-bot-ru
Version: 0.2.13
Summary: Telegram feedback bot
Home-page: https://github.com/gleb-chipiga/tg-feedback-bot-ru
Author: Gleb Chipiga
License: MIT
Platform: UNKNOWN
Classifier: Intended Audience :: Customer Service
Classifier: Intended Audience :: End Users/Desktop
Classifier: Intended Audience :: System Administrators
Classifier: Programming Language :: Python
Classifier: Programming Language :: Python :: 3
Classifier: Programming Language :: Python :: 3.9
Classifier: License :: OSI Approved :: MIT License
Classifier: Development Status :: 3 - Alpha
Classifier: Operating System :: POSIX
Classifier: Operating System :: MacOS :: MacOS X
Classifier: Operating System :: Microsoft :: Windows
Classifier: Topic :: Internet
Classifier: Topic :: Communications :: Chat
Classifier: Framework :: AsyncIO
Requires-Python: >=3.9
License-File: LICENSE
Requires-Dist: aiotgbot[sqlite] (<0.11.0,>=0.10.1)
Requires-Dist: aiojobs
Requires-Dist: aiojobs-stubs (>=0.2.2.post1)
Requires-Dist: attrs
Requires-Dist: uvloop (>=0.15.2)
Requires-Dist: more-itertools
Requires-Dist: pyyaml
